vectorslow/__init__.py
vectorslow/joke.py
vectorslow-1.3.dist-info/METADATA
vectorslow-1.3.dist-info/WHEEL
vectorslow-1.3.dist-info/top_level.txt
vectorslow-1.3.dist-info/RECORD
